MANIFEST.in
README.md
setup.py
examples/temporary_directory.py
sptempdir/__init__.py
sptempdir/temporary_directory.py
sptempdir.egg-info/PKG-INFO
sptempdir.egg-info/SOURCES.txt
sptempdir.egg-info/dependency_links.txt
sptempdir.egg-info/top_level.txt