Metadata-Version: 1.1
Name: sptempdir
Version: 0.1.5
Summary: This module generates temporary directories
Home-page: https://github.com/aleskrejcicz/sptempdir
Author: Ales Krejci
Author-email: aleskrejcicz@gmail.com
License: BSD
Keywords: tempdir,sptempdir,temporary directory,directory,temporary
Platform: any
Classifier: License :: OSI Approved :: BSD License
Classifier: Programming Language :: Python
Classifier: Programming Language :: Python :: 2.7
Classifier: Programming Language :: Python :: 3.2
Classifier: Programming Language :: Python :: 3.3
Classifier: Programming Language :: Python :: 3.4
Classifier: Programming Language :: Python :: 3.5
Classifier: Programming Language :: Python :: 3.6
